{
  "Version": 1,
  "WorldDescription": {
    "islandId": "",
    "WorldName": "My Windrose World",
    "CreationTime": 0,
    "WorldPresetType": "Custom",
    "WorldSettings": {
      "BoolParameters": {
        "{\"TagName\": \"WDS.Parameter.Coop.SharedQuests\"}": true,
        "{\"TagName\": \"WDS.Parameter.EasyExplore\"}": false
      },
      "FloatParameters": {
        "{\"TagName\": \"WDS.Parameter.MobHealthMultiplier\"}": 1.0,
        "{\"TagName\": \"WDS.Parameter.MobDamageMultiplier\"}": 1.0,
        "{\"TagName\": \"WDS.Parameter.ShipsHealthMultiplier\"}": 1.0,
        "{\"TagName\": \"WDS.Parameter.ShipsDamageMultiplier\"}": 1.0,
        "{\"TagName\": \"WDS.Parameter.BoardingDifficultyMultiplier\"}": 1.0,
        "{\"TagName\": \"WDS.Parameter.Coop.StatsCorrectionModifier\"}": 1.0,
        "{\"TagName\": \"WDS.Parameter.Coop.ShipStatsCorrectionModifier\"}": 1.0
      },
      "TagParameters": {
        "{\"TagName\": \"WDS.Parameter.CombatDifficulty\"}": {
          "TagName": "WDS.Parameter.CombatDifficulty.Normal"
        }
      }
    }
  }
}